<?xml version="1.0" encoding="UTF-8"?>
<MMDModel>
    <globalSettings>
        <fileType>PMX</fileType>
        <fileVersion>2.000000</fileVersion>
        <modelNameJp>アリシア・ソリッド　ビーム彫刻刀</modelNameJp>
        <modelNameEn>Alicia&#x20;Solids&#x20;beam&#x20;engraving&#x20;knife.&#x20;</modelNameEn>
        <commentJp>このビーム彫刻刀があれば　どんなものでも　モデリングできるぞ！！&#xD;&#xA;&#xD;&#xA;デザイン：&#x20;&#x20;&#x20;黒星紅白&#xD;&#xA;モデリング：&#x20;&#x20;雨刻憩&#xD;&#xA;&#xD;&#xA;(C)dwango,&#x20;inc.&#x20;All&#x20;rights&#x20;reserved.&#xD;&#xA;</commentJp>
        <commentEn>(C)dwango,&#x20;inc.&#x20;All&#x20;rights&#x20;reserved.&#xD;&#xA;</commentEn>
        <numVertex>6790</numVertex>
        <numIndex>26016</numIndex>
        <vertexScale>8.000000</vertexScale>
        <importScale>0.010000</importScale>
    </globalSettings>
    <textureList>
        <Texture>
            <fileName>Alicia_rod.tga</fileName>
        </Texture>
        <Texture>
            <fileName>rod_s.bmp</fileName>
        </Texture>
        <Texture>
            <fileName>ramp_s.bmp</fileName>
        </Texture>
        <Texture>
            <fileName>blade_s.bmp</fileName>
        </Texture>
        <Texture>
            <fileName>toon0.bmp</fileName>
        </Texture>
        <Texture>
            <fileName>toon01.bmp</fileName>
        </Texture>
        <Texture>
            <fileName>toon02.bmp</fileName>
        </Texture>
        <Texture>
            <fileName>toon03.bmp</fileName>
        </Texture>
        <Texture>
            <fileName>toon04.bmp</fileName>
        </Texture>
        <Texture>
            <fileName>toon05.bmp</fileName>
        </Texture>
        <Texture>
            <fileName>toon06.bmp</fileName>
        </Texture>
        <Texture>
            <fileName>toon07.bmp</fileName>
        </Texture>
        <Texture>
            <fileName>toon08.bmp</fileName>
        </Texture>
        <Texture>
            <fileName>toon09.bmp</fileName>
        </Texture>
        <Texture>
            <fileName>toon10.bmp</fileName>
        </Texture>
    </textureList>
    <materialList>
        <Material>
            <nameJp>main</nameJp>
            <nameEn></nameEn>
            <materialName>0</materialName>
            <diffuse>
                <r>1.000000</r>
                <g>1.000000</g>
                <b>1.000000</b>
                <a>1.000000</a>
            </diffuse>
            <specular>
                <r>0.000000</r>
                <g>0.000000</g>
                <b>0.000000</b>
            </specular>
            <shiness>3.200000</shiness>
            <ambient>
                <r>1.000000</r>
                <g>1.000000</g>
                <b>1.000000</b>
            </ambient>
            <sphereMode>Adding</sphereMode>
            <toonID>1</toonID>
            <edgeColor>
                <r>0.270588</r>
                <g>0.227451</g>
                <b>0.211765</b>
                <a>0.600000</a>
            </edgeColor>
            <edgeSize>0.960000</edgeSize>
            <textureID>0</textureID>
            <additionalTextureID>1</additionalTextureID>
            <toonTextureID>-1</toonTextureID>
            <flags>31</flags>
            <isDrawBothFaces>1</isDrawBothFaces>
            <isDrawGroundShadow>1</isDrawGroundShadow>
            <isDrawSelfShadowMap>1</isDrawSelfShadowMap>
            <isDrawSelfShadow>1</isDrawSelfShadow>
            <isDrawEdge>1</isDrawEdge>
            <numIndex>13566</numIndex>
        </Material>
        <Material>
            <nameJp>star</nameJp>
            <nameEn></nameEn>
            <materialName>1</materialName>
            <diffuse>
                <r>1.000000</r>
                <g>1.000000</g>
                <b>1.000000</b>
                <a>1.000000</a>
            </diffuse>
            <specular>
                <r>0.000000</r>
                <g>0.000000</g>
                <b>0.000000</b>
            </specular>
            <shiness>3.200000</shiness>
            <ambient>
                <r>1.000000</r>
                <g>1.000000</g>
                <b>1.000000</b>
            </ambient>
            <sphereMode>None</sphereMode>
            <toonID>0</toonID>
            <edgeColor>
                <r>0.270588</r>
                <g>0.227451</g>
                <b>0.211765</b>
                <a>0.600000</a>
            </edgeColor>
            <edgeSize>0.960000</edgeSize>
            <textureID>0</textureID>
            <additionalTextureID>-1</additionalTextureID>
            <toonTextureID>-1</toonTextureID>
            <flags>0</flags>
            <isDrawBothFaces>0</isDrawBothFaces>
            <isDrawGroundShadow>0</isDrawGroundShadow>
            <isDrawSelfShadowMap>0</isDrawSelfShadowMap>
            <isDrawSelfShadow>0</isDrawSelfShadow>
            <isDrawEdge>0</isDrawEdge>
            <numIndex>114</numIndex>
        </Material>
        <Material>
            <nameJp>ramp_back</nameJp>
            <nameEn></nameEn>
            <materialName>2</materialName>
            <diffuse>
                <r>1.000000</r>
                <g>1.000000</g>
                <b>1.000000</b>
                <a>1.000000</a>
            </diffuse>
            <specular>
                <r>0.000000</r>
                <g>0.000000</g>
                <b>0.000000</b>
            </specular>
            <shiness>3.200000</shiness>
            <ambient>
                <r>1.000000</r>
                <g>1.000000</g>
                <b>1.000000</b>
            </ambient>
            <sphereMode>None</sphereMode>
            <toonID>0</toonID>
            <edgeColor>
                <r>0.000000</r>
                <g>0.000000</g>
                <b>0.000000</b>
                <a>1.000000</a>
            </edgeColor>
            <edgeSize>1.200000</edgeSize>
            <textureID>0</textureID>
            <additionalTextureID>-1</additionalTextureID>
            <toonTextureID>-1</toonTextureID>
            <flags>2</flags>
            <isDrawBothFaces>0</isDrawBothFaces>
            <isDrawGroundShadow>1</isDrawGroundShadow>
            <isDrawSelfShadowMap>0</isDrawSelfShadowMap>
            <isDrawSelfShadow>0</isDrawSelfShadow>
            <isDrawEdge>0</isDrawEdge>
            <numIndex>1824</numIndex>
        </Material>
        <Material>
            <nameJp>ramp_in</nameJp>
            <nameEn></nameEn>
            <materialName>3</materialName>
            <diffuse>
                <r>1.000000</r>
                <g>1.000000</g>
                <b>1.000000</b>
                <a>1.000000</a>
            </diffuse>
            <specular>
                <r>0.000000</r>
                <g>0.000000</g>
                <b>0.000000</b>
            </specular>
            <shiness>3.200000</shiness>
            <ambient>
                <r>1.000000</r>
                <g>1.000000</g>
                <b>1.000000</b>
            </ambient>
            <sphereMode>Adding</sphereMode>
            <toonID>0</toonID>
            <edgeColor>
                <r>0.000000</r>
                <g>0.000000</g>
                <b>0.000000</b>
                <a>1.000000</a>
            </edgeColor>
            <edgeSize>1.200000</edgeSize>
            <textureID>0</textureID>
            <additionalTextureID>2</additionalTextureID>
            <toonTextureID>-1</toonTextureID>
            <flags>0</flags>
            <isDrawBothFaces>0</isDrawBothFaces>
            <isDrawGroundShadow>0</isDrawGroundShadow>
            <isDrawSelfShadowMap>0</isDrawSelfShadowMap>
            <isDrawSelfShadow>0</isDrawSelfShadow>
            <isDrawEdge>0</isDrawEdge>
            <numIndex>3000</numIndex>
        </Material>
        <Material>
            <nameJp>ramp_outside</nameJp>
            <nameEn></nameEn>
            <materialName>4</materialName>
            <diffuse>
                <r>1.000000</r>
                <g>1.000000</g>
                <b>1.000000</b>
                <a>1.000000</a>
            </diffuse>
            <specular>
                <r>0.000000</r>
                <g>0.000000</g>
                <b>0.000000</b>
            </specular>
            <shiness>3.200000</shiness>
            <ambient>
                <r>1.000000</r>
                <g>1.000000</g>
                <b>1.000000</b>
            </ambient>
            <sphereMode>Adding</sphereMode>
            <toonID>0</toonID>
            <edgeColor>
                <r>1.000000</r>
                <g>1.000000</g>
                <b>1.000000</b>
                <a>0.600000</a>
            </edgeColor>
            <edgeSize>0.960000</edgeSize>
            <textureID>0</textureID>
            <additionalTextureID>2</additionalTextureID>
            <toonTextureID>-1</toonTextureID>
            <flags>16</flags>
            <isDrawBothFaces>0</isDrawBothFaces>
            <isDrawGroundShadow>0</isDrawGroundShadow>
            <isDrawSelfShadowMap>0</isDrawSelfShadowMap>
            <isDrawSelfShadow>0</isDrawSelfShadow>
            <isDrawEdge>1</isDrawEdge>
            <numIndex>2400</numIndex>
        </Material>
        <Material>
            <nameJp>back</nameJp>
            <nameEn></nameEn>
            <materialName>5</materialName>
            <diffuse>
                <r>1.000000</r>
                <g>1.000000</g>
                <b>1.000000</b>
                <a>1.000000</a>
            </diffuse>
            <specular>
                <r>0.000000</r>
                <g>0.000000</g>
                <b>0.000000</b>
            </specular>
            <shiness>3.200000</shiness>
            <ambient>
                <r>1.000000</r>
                <g>1.000000</g>
                <b>1.000000</b>
            </ambient>
            <sphereMode>None</sphereMode>
            <toonID>0</toonID>
            <edgeColor>
                <r>0.000000</r>
                <g>0.000000</g>
                <b>0.000000</b>
                <a>1.000000</a>
            </edgeColor>
            <edgeSize>1.200000</edgeSize>
            <textureID>0</textureID>
            <additionalTextureID>-1</additionalTextureID>
            <toonTextureID>-1</toonTextureID>
            <flags>0</flags>
            <isDrawBothFaces>0</isDrawBothFaces>
            <isDrawGroundShadow>0</isDrawGroundShadow>
            <isDrawSelfShadowMap>0</isDrawSelfShadowMap>
            <isDrawSelfShadow>0</isDrawSelfShadow>
            <isDrawEdge>0</isDrawEdge>
            <numIndex>3480</numIndex>
        </Material>
        <Material>
            <nameJp>blade</nameJp>
            <nameEn></nameEn>
            <materialName>6</materialName>
            <diffuse>
                <r>1.000000</r>
                <g>1.000000</g>
                <b>1.000000</b>
                <a>1.000000</a>
            </diffuse>
            <specular>
                <r>0.000000</r>
                <g>0.000000</g>
                <b>0.000000</b>
            </specular>
            <shiness>3.200000</shiness>
            <ambient>
                <r>1.000000</r>
                <g>1.000000</g>
                <b>1.000000</b>
            </ambient>
            <sphereMode>Multiply</sphereMode>
            <toonID>0</toonID>
            <edgeColor>
                <r>0.000000</r>
                <g>0.000000</g>
                <b>0.000000</b>
                <a>1.000000</a>
            </edgeColor>
            <edgeSize>1.200000</edgeSize>
            <textureID>0</textureID>
            <additionalTextureID>3</additionalTextureID>
            <toonTextureID>-1</toonTextureID>
            <flags>0</flags>
            <isDrawBothFaces>0</isDrawBothFaces>
            <isDrawGroundShadow>0</isDrawGroundShadow>
            <isDrawSelfShadowMap>0</isDrawSelfShadowMap>
            <isDrawSelfShadow>0</isDrawSelfShadow>
            <isDrawEdge>0</isDrawEdge>
            <numIndex>1632</numIndex>
        </Material>
    </materialList>
    <boneList>
        <Bone>
            <nameJp>センター</nameJp>
            <nameEn>center</nameEn>
            <skeletonName>0.joint_センター</skeletonName>
            <parentBoneID>1</parentBoneID>
            <sortedBoneID>1</sortedBoneID>
            <originalParentBoneID>-1</originalParentBoneID>
            <originalSortedBoneID>0</originalSortedBoneID>
            <origin>
                <x>0.000000</x>
                <y>0.000000</y>
                <z>0.000000</z>
            </origin>
            <additionalFlags>0</additionalFlags>
            <isLimitAngleX>0</isLimitAngleX>
            <transformLayerID>0</transformLayerID>
            <flags>30</flags>
            <destination>0</destination>
            <isRotate>1</isRotate>
            <isTranslate>1</isTranslate>
            <isVisible>1</isVisible>
            <isControllable>1</isControllable>
            <isIK>0</isIK>
            <inherenceLocal>0</inherenceLocal>
            <isInherenceRotate>0</isInherenceRotate>
            <isInherenceTranslate>0</isInherenceTranslate>
            <isFixedAxis>0</isFixedAxis>
            <isLocalAxis>0</isLocalAxis>
            <isTransformAfterPhysics>0</isTransformAfterPhysics>
            <isTransformExternalParent>0</isTransformExternalParent>
            <destinationOrigin>
                <x>0.000000</x>
                <y>0.000000</y>
                <z>0.000000</z>
            </destinationOrigin>
        </Bone>
        <Bone>
            <additionalFlags>2147483648</additionalFlags>
            <nameJp>ルート</nameJp>
            <nameEn>Root</nameEn>
            <skeletonName>1.!Root</skeletonName>
            <parentBoneID>-1</parentBoneID>
            <sortedBoneID>0</sortedBoneID>
            <originalParentBoneID>-1</originalParentBoneID>
            <originalSortedBoneID>-1</originalSortedBoneID>
        </Bone>
    </boneList>
    <ikList />
    <morphList>
        <Morph>
            <nameJp>ビーム出</nameJp>
            <nameEn></nameEn>
            <additionalFlags>0</additionalFlags>
            <isMorphBaseVertex>0</isMorphBaseVertex>
            <morphCategory>Other</morphCategory>
            <morphType>Vertex</morphType>
        </Morph>
        <Morph>
            <nameJp>ビーム長</nameJp>
            <nameEn></nameEn>
            <additionalFlags>0</additionalFlags>
            <isMorphBaseVertex>0</isMorphBaseVertex>
            <morphCategory>Other</morphCategory>
            <morphType>Vertex</morphType>
        </Morph>
    </morphList>
    <displayFrameList>
        <DisplayFrame>
            <nameJp>Root</nameJp>
            <nameEn>Root</nameEn>
            <additionalFlags>1</additionalFlags>
            <isSpecial>1</isSpecial>
            <itemList>
                <Item>
                    <type>Bone</type>
                    <index>0</index>
                </Item>
            </itemList>
        </DisplayFrame>
        <DisplayFrame>
            <nameJp>表情</nameJp>
            <nameEn>Exp</nameEn>
            <additionalFlags>1</additionalFlags>
            <isSpecial>1</isSpecial>
            <itemList>
                <Item>
                    <type>Morph</type>
                    <index>0</index>
                </Item>
                <Item>
                    <type>Morph</type>
                    <index>1</index>
                </Item>
            </itemList>
        </DisplayFrame>
    </displayFrameList>
    <rigidBodyList />
    <jointList />
</MMDModel>
